app.py
util.py
song_and_spell/__init__.py
song_and_spell/app.py
song_and_spell/util.py
song_and_spell/static/templates/add_word.html
song_and_spell/static/templates/base.html
song_and_spell/static/templates/footer.html
song_and_spell/static/templates/header.html
song_and_spell/static/templates/index.html
song_and_spell-0.20.0.dist-info/METADATA
song_and_spell-0.20.0.dist-info/WHEEL
song_and_spell-0.20.0.dist-info/entry_points.txt
song_and_spell-0.20.0.dist-info/top_level.txt
song_and_spell-0.20.0.dist-info/RECORD
