Metadata-Version: 2.1
Name: song-and-spell
Version: 0.20.0
Summary: A configurable, mutable toddler radio that encourages spelling
Home-page: https://github.com/cboddy/song-and-spell
Author: Chris Boddy
Author-email: chris@boddy.im
License: UNKNOWN
Platform: UNKNOWN
Requires-Dist: appdirs
Requires-Dist: backcall
Requires-Dist: black
Requires-Dist: click
Requires-Dist: dataclasses
Requires-Dist: decorator
Requires-Dist: evdev
Requires-Dist: Flask
Requires-Dist: ipython
Requires-Dist: ipython-genutils
Requires-Dist: itsdangerous
Requires-Dist: jedi
Requires-Dist: Jinja2
Requires-Dist: MarkupSafe
Requires-Dist: mypy-extensions
Requires-Dist: parso
Requires-Dist: pathspec
Requires-Dist: pexpect
Requires-Dist: pickleshare
Requires-Dist: prompt-toolkit
Requires-Dist: ptyprocess
Requires-Dist: Pygments
Requires-Dist: pynput
Requires-Dist: python-xlib
Requires-Dist: regex
Requires-Dist: six
Requires-Dist: toml
Requires-Dist: traitlets
Requires-Dist: typed-ast
Requires-Dist: typing-extensions
Requires-Dist: wcwidth
Requires-Dist: Werkzeug
Requires-Dist: wheel
Requires-Dist: xdg
Requires-Dist: youtube-dl
